LICENSE
django_autoutils/__init__.py
django_autoutils/admin_numeric_filter/__init__.py
django_autoutils/admin_numeric_filter/admin.py
django_autoutils/admin_numeric_filter/forms.py
django_autoutils/admin_numeric_filter/static/css/admin-numeric-filter.css
django_autoutils/admin_numeric_filter/static/js/admin-numeric-filter.js
django_autoutils/admin_numeric_filter/static/js/nouislider.min.css
django_autoutils/admin_numeric_filter/static/js/nouislider.min.js
django_autoutils/admin_numeric_filter/static/js/wNumb.min.js
django_autoutils/admin_numeric_filter/templates/admin/filter_numeric_range.html
django_autoutils/admin_numeric_filter/templates/admin/filter_numeric_single.html
django_autoutils/admin_numeric_filter/templates/admin/filter_numeric_slider.html
django_autoutils/admin_utils.py
django_autoutils/exceptions.py
django_autoutils/html_tag.py
django_autoutils/managers.py
django_autoutils/model_utils.py
django_autoutils/serializer_utils.py
django_autoutils/utils.py
django_autoutils-2.1.1.dist-info/LICENSE
django_autoutils-2.1.1.dist-info/METADATA
django_autoutils-2.1.1.dist-info/WHEEL
django_autoutils-2.1.1.dist-info/RECORD
