Metadata-Version: 2.1
Name: django-autoutils
Version: 2.1.1
Summary: Some Good Function In Django
Home-page: https://github.com/rezazeiny/django-autoutils
License: MIT
Keywords: django-autoutils
Author: Reza Zeiny
Author-email: rezazeiny1998@gmail.com
Requires-Python: >=3.12,<4.0
Classifier: License :: OSI Approved :: MIT License
Classifier: Operating System :: OS Independent
Classifier: Programming Language :: Python :: 3
Classifier: Programming Language :: Python :: 3.12
Requires-Dist: Django (>=5.0)
Requires-Dist: Markdown (>=3.0,<4.0)
Requires-Dist: Pillow (>=10.0)
Requires-Dist: Pygments (>=2.0,<3.0)
Requires-Dist: autoutils (>=1.0)
Requires-Dist: django-admin-autocomplete-filter (>=0.7,<1.0)
Requires-Dist: django-admin-list-filter-dropdown (>=1.0,<2.0)
Requires-Dist: djangorestframework (>=3.15)
Project-URL: Repository, https://github.com/rezazeiny/django-autoutils
